{"expireTime":9007200822430773000,"key":"gatsby-plugin-mdx-entire-payload-9aeb65215777fbc74905a854766758e0-","val":{"mdast":{"type":"root","children":[{"type":"import","value":"import DefaultLayout from \"/Users/tflonlineuser/Creative Cloud Files/TFL/_DesignLanguage/DesignSystemSite/TfL-Design-Library/node_modules/gatsby-theme-carbon/src/templates/Default.js\"","position":{"start":{"line":3,"column":1,"offset":2},"end":{"line":3,"column":184,"offset":185},"indent":[]}},{"type":"export","default":true,"value":"export default DefaultLayout","position":{"start":{"line":5,"column":1,"offset":187},"end":{"line":5,"column":29,"offset":215},"indent":[]}},{"type":"jsx","value":"<PageDescription>","position":{"start":{"line":8,"column":1,"offset":218},"end":{"line":8,"column":18,"offset":235},"indent":[]}},{"type":"paragraph","children":[{"type":"text","value":"Gatsby themes allow you to override configuration from the theme by defining the same property in your ","position":{"start":{"line":10,"column":1,"offset":237},"end":{"line":10,"column":104,"offset":340},"indent":[]}},{"type":"inlineCode","value":"gatsby-config.js","position":{"start":{"line":10,"column":104,"offset":340},"end":{"line":10,"column":122,"offset":358},"indent":[]}},{"type":"text","value":" at the root of your project. You can see the default configuration provided by the theme's ","position":{"start":{"line":10,"column":122,"offset":358},"end":{"line":10,"column":214,"offset":450},"indent":[]}},{"type":"link","title":null,"url":"https://github.com/carbon-design-system/gatsby-theme-carbon/blob/master/packages/gatsby-theme-carbon/gatsby-config.js","children":[{"type":"inlineCode","value":"gatsby-config.js","position":{"start":{"line":10,"column":215,"offset":451},"end":{"line":10,"column":233,"offset":469},"indent":[]}}],"position":{"start":{"line":10,"column":214,"offset":450},"end":{"line":10,"column":353,"offset":589},"indent":[]}},{"type":"text","value":" file.","position":{"start":{"line":10,"column":353,"offset":589},"end":{"line":10,"column":359,"offset":595},"indent":[]}}],"position":{"start":{"line":10,"column":1,"offset":237},"end":{"line":10,"column":359,"offset":595},"indent":[]}},{"type":"jsx","value":"</PageDescription>","position":{"start":{"line":12,"column":1,"offset":597},"end":{"line":12,"column":19,"offset":615},"indent":[]}},{"type":"jsx","value":"<AnchorLinks>\n  <AnchorLink>Site Title and Description</AnchorLink>\n  <AnchorLink>Manifest</AnchorLink>\n  <AnchorLink>Favicon</AnchorLink>\n  <AnchorLink>Additional font weights</AnchorLink>\n  <AnchorLink>Image Compression</AnchorLink>\n  <AnchorLink>Global Search</AnchorLink>\n  <AnchorLink>Edit on Github link</AnchorLink>\n</AnchorLinks>","position":{"start":{"line":14,"column":1,"offset":617},"end":{"line":22,"column":15,"offset":954},"indent":[1,1,1,1,1,1,1,1]}},{"type":"heading","depth":2,"children":[{"type":"text","value":"Site Title and Description","position":{"start":{"line":24,"column":4,"offset":959},"end":{"line":24,"column":30,"offset":985},"indent":[]}}],"position":{"start":{"line":24,"column":1,"offset":956},"end":{"line":24,"column":30,"offset":985},"indent":[]}},{"type":"paragraph","children":[{"type":"text","value":"To add a title and description to each page, simply provide them to siteMetadata in your ","position":{"start":{"line":26,"column":1,"offset":987},"end":{"line":26,"column":90,"offset":1076},"indent":[]}},{"type":"inlineCode","value":"gatsby-config.js","position":{"start":{"line":26,"column":90,"offset":1076},"end":{"line":26,"column":108,"offset":1094},"indent":[]}},{"type":"text","value":" file.","position":{"start":{"line":26,"column":108,"offset":1094},"end":{"line":26,"column":114,"offset":1100},"indent":[]}}],"position":{"start":{"line":26,"column":1,"offset":987},"end":{"line":26,"column":114,"offset":1100},"indent":[]}},{"type":"code","lang":"js","meta":null,"value":"module.exports = {\n  siteMetadata: {\n    title: 'Gatsby Theme Carbon',\n    description: 'A Gatsby theme for the carbon design system',\n    keywords: 'gatsby,theme,carbon',\n  },\n  plugins: ['gatsby-theme-carbon'],\n};","position":{"start":{"line":28,"column":1,"offset":1102},"end":{"line":37,"column":4,"offset":1327},"indent":[1,1,1,1,1,1,1,1,1]}},{"type":"heading","depth":2,"children":[{"type":"text","value":"Manifest","position":{"start":{"line":39,"column":4,"offset":1332},"end":{"line":39,"column":12,"offset":1340},"indent":[]}}],"position":{"start":{"line":39,"column":1,"offset":1329},"end":{"line":39,"column":12,"offset":1340},"indent":[]}},{"type":"paragraph","children":[{"type":"text","value":"One of the first configurations should be to override the default manifest options, you can do this in ","position":{"start":{"line":41,"column":1,"offset":1342},"end":{"line":41,"column":104,"offset":1445},"indent":[]}},{"type":"inlineCode","value":"gatsby-config.js","position":{"start":{"line":41,"column":104,"offset":1445},"end":{"line":41,"column":122,"offset":1463},"indent":[]}},{"type":"text","value":". Any options you don't set, will be provided by the theme. See the example project.","position":{"start":{"line":41,"column":122,"offset":1463},"end":{"line":41,"column":206,"offset":1547},"indent":[]}}],"position":{"start":{"line":41,"column":1,"offset":1342},"end":{"line":41,"column":206,"offset":1547},"indent":[]}},{"type":"code","lang":"js","meta":null,"value":"siteMetadata: {\n    title: 'Gatsby Theme Carbon',\n  },\n  plugins: [\n    'gatsby-theme-carbon',\n    {\n      resolve: 'gatsby-plugin-manifest',\n      options: {\n        name: 'Carbon Design Gatsby Theme',\n        short_name: 'Gatsby Theme Carbon',\n        start_url: '/',\n        background_color: '#ffffff',\n        theme_color: '#0062ff',\n        display: 'browser',\n      },\n    },\n  ],","position":{"start":{"line":43,"column":1,"offset":1549},"end":{"line":61,"column":4,"offset":1946},"indent":[1,1,1,1,1,1,1,1,1,1,1,1,1,1,1,1,1,1]}},{"type":"heading","depth":2,"children":[{"type":"text","value":"Favicon","position":{"start":{"line":63,"column":4,"offset":1951},"end":{"line":63,"column":11,"offset":1958},"indent":[]}}],"position":{"start":{"line":63,"column":1,"offset":1948},"end":{"line":63,"column":11,"offset":1958},"indent":[]}},{"type":"paragraph","children":[{"type":"text","value":"If you need to override the default favicon, you can do so by passing a relative path to the icon. It's recommended to provide a 512 x 512 version.","position":{"start":{"line":65,"column":1,"offset":1960},"end":{"line":65,"column":148,"offset":2107},"indent":[]}}],"position":{"start":{"line":65,"column":1,"offset":1960},"end":{"line":65,"column":148,"offset":2107},"indent":[]}},{"type":"paragraph","children":[{"type":"strong","children":[{"type":"text","value":"IMPORTANT:","position":{"start":{"line":67,"column":3,"offset":2111},"end":{"line":67,"column":13,"offset":2121},"indent":[]}}],"position":{"start":{"line":67,"column":1,"offset":2109},"end":{"line":67,"column":15,"offset":2123},"indent":[]}},{"type":"text","value":" For best results, if you’re providing an icon for generation it should be…","position":{"start":{"line":67,"column":15,"offset":2123},"end":{"line":67,"column":90,"offset":2198},"indent":[]}}],"position":{"start":{"line":67,"column":1,"offset":2109},"end":{"line":67,"column":90,"offset":2198},"indent":[]}},{"type":"list","ordered":false,"start":null,"spread":false,"children":[{"type":"listItem","spread":false,"checked":null,"children":[{"type":"paragraph","children":[{"type":"text","value":"at least as big as the largest icon being generated (512x512 by default).","position":{"start":{"line":69,"column":3,"offset":2202},"end":{"line":69,"column":76,"offset":2275},"indent":[]}}],"position":{"start":{"line":69,"column":3,"offset":2202},"end":{"line":69,"column":76,"offset":2275},"indent":[]}}],"position":{"start":{"line":69,"column":1,"offset":2200},"end":{"line":69,"column":76,"offset":2275},"indent":[]}},{"type":"listItem","spread":false,"checked":null,"children":[{"type":"paragraph","children":[{"type":"text","value":"square (if it’s not, transparent bars will add to make it square).","position":{"start":{"line":70,"column":3,"offset":2278},"end":{"line":70,"column":69,"offset":2344},"indent":[]}}],"position":{"start":{"line":70,"column":3,"offset":2278},"end":{"line":70,"column":69,"offset":2344},"indent":[]}}],"position":{"start":{"line":70,"column":1,"offset":2276},"end":{"line":70,"column":69,"offset":2344},"indent":[]}},{"type":"listItem","spread":false,"checked":null,"children":[{"type":"paragraph","children":[{"type":"text","value":"of one of the follow formats: JPEG, PNG, WebP, TIFF, GIF or SVG.","position":{"start":{"line":71,"column":3,"offset":2347},"end":{"line":71,"column":67,"offset":2411},"indent":[]}}],"position":{"start":{"line":71,"column":3,"offset":2347},"end":{"line":71,"column":67,"offset":2411},"indent":[]}}],"position":{"start":{"line":71,"column":1,"offset":2345},"end":{"line":71,"column":67,"offset":2411},"indent":[]}}],"position":{"start":{"line":69,"column":1,"offset":2200},"end":{"line":71,"column":67,"offset":2411},"indent":[1,1]}},{"type":"code","lang":"js","meta":null,"value":"plugins: [\n    {\n      resolve: 'gatsby-theme-carbon',\n      options: {\n        iconPath: './src/images/custom-icon-512.png'\n      },\n    },\n  ],","position":{"start":{"line":73,"column":1,"offset":2413},"end":{"line":82,"column":4,"offset":2568},"indent":[1,1,1,1,1,1,1,1,1]}},{"type":"heading","depth":2,"children":[{"type":"text","value":"Additional font weights","position":{"start":{"line":84,"column":4,"offset":2573},"end":{"line":84,"column":27,"offset":2596},"indent":[]}}],"position":{"start":{"line":84,"column":1,"offset":2570},"end":{"line":84,"column":27,"offset":2596},"indent":[]}},{"type":"paragraph","children":[{"type":"text","value":"If needed, you can add support for additional Plex font weights. Don't forget to specify italics for the additional weights if needed.","position":{"start":{"line":86,"column":1,"offset":2598},"end":{"line":86,"column":135,"offset":2732},"indent":[]}}],"position":{"start":{"line":86,"column":1,"offset":2598},"end":{"line":86,"column":135,"offset":2732},"indent":[]}},{"type":"code","lang":"js","meta":null,"value":"plugins: [\n    {\n      resolve: 'gatsby-theme-carbon',\n      options: {\n\t\t// will get added to default [300, 400, 600]\n        additionalFontWeights: ['200', '200i]\n      },\n    },\n  ],","position":{"start":{"line":88,"column":1,"offset":2734},"end":{"line":98,"column":4,"offset":2929},"indent":[1,1,1,1,1,1,1,1,1,1]}},{"type":"heading","depth":2,"children":[{"type":"text","value":"Image Compression","position":{"start":{"line":100,"column":4,"offset":2934},"end":{"line":100,"column":21,"offset":2951},"indent":[]}}],"position":{"start":{"line":100,"column":1,"offset":2931},"end":{"line":100,"column":21,"offset":2951},"indent":[]}},{"type":"paragraph","children":[{"type":"text","value":"You can enable WebP by passing ","position":{"start":{"line":102,"column":1,"offset":2953},"end":{"line":102,"column":32,"offset":2984},"indent":[]}},{"type":"inlineCode","value":"withWebp: true","position":{"start":{"line":102,"column":32,"offset":2984},"end":{"line":102,"column":48,"offset":3000},"indent":[]}},{"type":"text","value":" or providing your own optimization level. See the gatsby-remark-images ","position":{"start":{"line":102,"column":48,"offset":3000},"end":{"line":102,"column":120,"offset":3072},"indent":[]}},{"type":"link","title":null,"url":"https://www.gatsbyjs.org/packages/gatsby-remark-images/#options","children":[{"type":"text","value":"plugin options","position":{"start":{"line":102,"column":121,"offset":3073},"end":{"line":102,"column":135,"offset":3087},"indent":[]}}],"position":{"start":{"line":102,"column":120,"offset":3072},"end":{"line":102,"column":201,"offset":3153},"indent":[]}},{"type":"text","value":".","position":{"start":{"line":102,"column":201,"offset":3153},"end":{"line":102,"column":202,"offset":3154},"indent":[]}}],"position":{"start":{"line":102,"column":1,"offset":2953},"end":{"line":102,"column":202,"offset":3154},"indent":[]}},{"type":"code","lang":"js","meta":null,"value":"module.exports = {\n  siteMetadata: {\n    title: 'Gatsby Theme Carbon',\n  },\n  plugins: [\n    {\n      resolve: 'gatsby-theme-carbon',\n      options: {\n        name: 'Gatsby Theme Carbon Starter',\n        shortName: 'Carbon Starter',\n        withWebp: true,\n      },\n    },\n  ],\n};","position":{"start":{"line":104,"column":1,"offset":3156},"end":{"line":120,"column":4,"offset":3445},"indent":[1,1,1,1,1,1,1,1,1,1,1,1,1,1,1,1]}},{"type":"heading","depth":2,"children":[{"type":"text","value":"Global Search","position":{"start":{"line":122,"column":4,"offset":3450},"end":{"line":122,"column":17,"offset":3463},"indent":[]}}],"position":{"start":{"line":122,"column":1,"offset":3447},"end":{"line":122,"column":17,"offset":3463},"indent":[]}},{"type":"paragraph","children":[{"type":"text","value":"The GlobalSearch component is disabled by default. If you'd like to implement search functionality, you'll need to follow these two steps:","position":{"start":{"line":124,"column":1,"offset":3465},"end":{"line":124,"column":139,"offset":3603},"indent":[]}}],"position":{"start":{"line":124,"column":1,"offset":3465},"end":{"line":124,"column":139,"offset":3603},"indent":[]}},{"type":"list","ordered":true,"start":1,"spread":false,"children":[{"type":"listItem","spread":false,"checked":null,"children":[{"type":"paragraph","children":[{"type":"text","value":"set the isSearchEnabled theme option to true","position":{"start":{"line":126,"column":4,"offset":3608},"end":{"line":126,"column":48,"offset":3652},"indent":[]}}],"position":{"start":{"line":126,"column":4,"offset":3608},"end":{"line":126,"column":48,"offset":3652},"indent":[]}}],"position":{"start":{"line":126,"column":1,"offset":3605},"end":{"line":126,"column":48,"offset":3652},"indent":[]}}],"position":{"start":{"line":126,"column":1,"offset":3605},"end":{"line":126,"column":48,"offset":3652},"indent":[]}},{"type":"code","lang":"js","meta":null,"value":"  plugins: [\n    {\n      resolve: 'gatsby-theme-carbon',\n      options: {\n        isSearchEnabled: true\n      },\n    },\n  ],","position":{"start":{"line":128,"column":1,"offset":3654},"end":{"line":137,"column":4,"offset":3788},"indent":[1,1,1,1,1,1,1,1,1]}},{"type":"list","ordered":true,"start":2,"spread":false,"children":[{"type":"listItem","spread":false,"checked":null,"children":[{"type":"paragraph","children":[{"type":"text","value":"Shadow the example search implementation at ","position":{"start":{"line":139,"column":4,"offset":3793},"end":{"line":139,"column":48,"offset":3837},"indent":[]}},{"type":"inlineCode","value":"/src/util/hooks/useSearch.js","position":{"start":{"line":139,"column":48,"offset":3837},"end":{"line":139,"column":78,"offset":3867},"indent":[]}}],"position":{"start":{"line":139,"column":4,"offset":3793},"end":{"line":139,"column":78,"offset":3867},"indent":[]}}],"position":{"start":{"line":139,"column":1,"offset":3790},"end":{"line":139,"column":78,"offset":3867},"indent":[]}}],"position":{"start":{"line":139,"column":1,"offset":3790},"end":{"line":139,"column":78,"offset":3867},"indent":[]}},{"type":"code","lang":"jsx","meta":null,"value":"import { useEffect } from 'react';\nconst useAlgoliaSearch = () => {\n  // ...\n};\n\nexport default useAlgoliaSearch;","position":{"start":{"line":141,"column":1,"offset":3869},"end":{"line":148,"column":4,"offset":3993},"indent":[1,1,1,1,1,1,1]}},{"type":"paragraph","children":[{"type":"text","value":"The example ","position":{"start":{"line":150,"column":1,"offset":3995},"end":{"line":150,"column":13,"offset":4007},"indent":[]}},{"type":"inlineCode","value":"useSearch","position":{"start":{"line":150,"column":13,"offset":4007},"end":{"line":150,"column":24,"offset":4018},"indent":[]}},{"type":"text","value":" hook demonstrates implementing search with ","position":{"start":{"line":150,"column":24,"offset":4018},"end":{"line":150,"column":68,"offset":4062},"indent":[]}},{"type":"link","title":null,"url":"https://www.algolia.com/","children":[{"type":"text","value":"Algolia","position":{"start":{"line":150,"column":69,"offset":4063},"end":{"line":150,"column":76,"offset":4070},"indent":[]}}],"position":{"start":{"line":150,"column":68,"offset":4062},"end":{"line":150,"column":103,"offset":4097},"indent":[]}},{"type":"text","value":". Algolia is free for open source libraries. You can shadow this hook and replace it with your Algolia credentials or a library of your choosing.","position":{"start":{"line":150,"column":103,"offset":4097},"end":{"line":150,"column":248,"offset":4242},"indent":[]}}],"position":{"start":{"line":150,"column":1,"offset":3995},"end":{"line":150,"column":248,"offset":4242},"indent":[]}},{"type":"heading","depth":2,"children":[{"type":"text","value":"Edit on GitHub link","position":{"start":{"line":152,"column":4,"offset":4247},"end":{"line":152,"column":23,"offset":4266},"indent":[]}}],"position":{"start":{"line":152,"column":1,"offset":4244},"end":{"line":152,"column":23,"offset":4266},"indent":[]}},{"type":"paragraph","children":[{"type":"text","value":"To add a link to the bottom of each page that points to the current page source in GitHub, provide an ","position":{"start":{"line":154,"column":1,"offset":4268},"end":{"line":154,"column":103,"offset":4370},"indent":[]}},{"type":"inlineCode","value":"repository","position":{"start":{"line":154,"column":103,"offset":4370},"end":{"line":154,"column":115,"offset":4382},"indent":[]}},{"type":"text","value":" object to ","position":{"start":{"line":154,"column":115,"offset":4382},"end":{"line":154,"column":126,"offset":4393},"indent":[]}},{"type":"inlineCode","value":"siteMetadata","position":{"start":{"line":154,"column":126,"offset":4393},"end":{"line":154,"column":140,"offset":4407},"indent":[]}},{"type":"text","value":" in your ","position":{"start":{"line":154,"column":140,"offset":4407},"end":{"line":154,"column":149,"offset":4416},"indent":[]}},{"type":"inlineCode","value":"gatsby-config.js","position":{"start":{"line":154,"column":149,"offset":4416},"end":{"line":154,"column":167,"offset":4434},"indent":[]}},{"type":"text","value":" file. You can provide a ","position":{"start":{"line":154,"column":167,"offset":4434},"end":{"line":154,"column":192,"offset":4459},"indent":[]}},{"type":"inlineCode","value":"baseUrl","position":{"start":{"line":154,"column":192,"offset":4459},"end":{"line":154,"column":201,"offset":4468},"indent":[]}},{"type":"text","value":", and if needed, the ","position":{"start":{"line":154,"column":201,"offset":4468},"end":{"line":154,"column":222,"offset":4489},"indent":[]}},{"type":"inlineCode","value":"subDirectory","position":{"start":{"line":154,"column":222,"offset":4489},"end":{"line":154,"column":236,"offset":4503},"indent":[]}},{"type":"text","value":" where your site source lives.","position":{"start":{"line":154,"column":236,"offset":4503},"end":{"line":154,"column":266,"offset":4533},"indent":[]}}],"position":{"start":{"line":154,"column":1,"offset":4268},"end":{"line":154,"column":266,"offset":4533},"indent":[]}},{"type":"code","lang":"js","meta":null,"value":"  plugins: [\n    {\n      resolve: 'gatsby-theme-carbon',\n      options: {\n        repository: {\n          baseUrl: 'https://github.com/carbon-design-system/gatsby-theme-carbon',\n          subDirectory: '/packages/example',\n        },\n      },\n    },\n  ],","position":{"start":{"line":156,"column":1,"offset":4535},"end":{"line":168,"column":4,"offset":4799},"indent":[1,1,1,1,1,1,1,1,1,1,1,1]}},{"type":"export","value":"export const _frontmatter = {}","position":{"start":{"line":171,"column":1,"offset":4802},"end":{"line":171,"column":31,"offset":4832},"indent":[]}}],"position":{"start":{"line":1,"column":1,"offset":0},"end":{"line":171,"column":31,"offset":4832}}},"scopeImports":[],"scopeIdentifiers":[],"rawMDXOutput":"/* @jsx mdx */\nimport { mdx } from '@mdx-js/react';\n/* @jsx mdx */\nimport DefaultLayout from \"/Users/tflonlineuser/Creative Cloud Files/TFL/_DesignLanguage/DesignSystemSite/TfL-Design-Library/node_modules/gatsby-theme-carbon/src/templates/Default.js\"\nexport const _frontmatter = {};\nconst makeShortcode = name => function MDXDefaultShortcode(props) {\n  console.warn(\"Component \" + name + \" was not imported, exported, or provided by MDXProvider as global scope\")\n  return <div {...props}/>\n};\nconst PageDescription = makeShortcode(\"PageDescription\");\nconst AnchorLinks = makeShortcode(\"AnchorLinks\");\nconst AnchorLink = makeShortcode(\"AnchorLink\");\nconst layoutProps = {\n  _frontmatter\n};\nconst MDXLayout = DefaultLayout\nexport default function MDXContent({\n  components,\n  ...props\n}) {\n  return <MDXLayout {...layoutProps} {...props} components={components} mdxType=\"MDXLayout\">\n\n\n    <PageDescription mdxType=\"PageDescription\">\n      <p>{`Gatsby themes allow you to override configuration from the theme by defining the same property in your `}<inlineCode parentName=\"p\">{`gatsby-config.js`}</inlineCode>{` at the root of your project. You can see the default configuration provided by the theme’s `}<a parentName=\"p\" {...{\n          \"href\": \"https://github.com/carbon-design-system/gatsby-theme-carbon/blob/master/packages/gatsby-theme-carbon/gatsby-config.js\"\n        }}><inlineCode parentName=\"a\">{`gatsby-config.js`}</inlineCode></a>{` file.`}</p>\n    </PageDescription>\n    <AnchorLinks mdxType=\"AnchorLinks\">\n  <AnchorLink mdxType=\"AnchorLink\">Site Title and Description</AnchorLink>\n  <AnchorLink mdxType=\"AnchorLink\">Manifest</AnchorLink>\n  <AnchorLink mdxType=\"AnchorLink\">Favicon</AnchorLink>\n  <AnchorLink mdxType=\"AnchorLink\">Additional font weights</AnchorLink>\n  <AnchorLink mdxType=\"AnchorLink\">Image Compression</AnchorLink>\n  <AnchorLink mdxType=\"AnchorLink\">Global Search</AnchorLink>\n  <AnchorLink mdxType=\"AnchorLink\">Edit on Github link</AnchorLink>\n    </AnchorLinks>\n    <h2 {...{\n      \"id\": \"site-title-and-description\"\n    }}>{`Site Title and Description`}</h2>\n    <p>{`To add a title and description to each page, simply provide them to siteMetadata in your `}<inlineCode parentName=\"p\">{`gatsby-config.js`}</inlineCode>{` file.`}</p>\n    <pre><code parentName=\"pre\" {...{\n        \"className\": \"language-js\"\n      }}>{`module.exports = {\n  siteMetadata: {\n    title: 'Gatsby Theme Carbon',\n    description: 'A Gatsby theme for the carbon design system',\n    keywords: 'gatsby,theme,carbon',\n  },\n  plugins: ['gatsby-theme-carbon'],\n};\n`}</code></pre>\n    <h2 {...{\n      \"id\": \"manifest\"\n    }}>{`Manifest`}</h2>\n    <p>{`One of the first configurations should be to override the default manifest options, you can do this in `}<inlineCode parentName=\"p\">{`gatsby-config.js`}</inlineCode>{`. Any options you don’t set, will be provided by the theme. See the example project.`}</p>\n    <pre><code parentName=\"pre\" {...{\n        \"className\": \"language-js\"\n      }}>{`siteMetadata: {\n    title: 'Gatsby Theme Carbon',\n  },\n  plugins: [\n    'gatsby-theme-carbon',\n    {\n      resolve: 'gatsby-plugin-manifest',\n      options: {\n        name: 'Carbon Design Gatsby Theme',\n        short_name: 'Gatsby Theme Carbon',\n        start_url: '/',\n        background_color: '#ffffff',\n        theme_color: '#0062ff',\n        display: 'browser',\n      },\n    },\n  ],\n`}</code></pre>\n    <h2 {...{\n      \"id\": \"favicon\"\n    }}>{`Favicon`}</h2>\n    <p>{`If you need to override the default favicon, you can do so by passing a relative path to the icon. It’s recommended to provide a 512 x 512 version.`}</p>\n    <p><strong parentName=\"p\">{`IMPORTANT:`}</strong>{` For best results, if you’re providing an icon for generation it should be…`}</p>\n    <ul>\n      <li parentName=\"ul\">{`at least as big as the largest icon being generated (512x512 by default).`}</li>\n      <li parentName=\"ul\">{`square (if it’s not, transparent bars will add to make it square).`}</li>\n      <li parentName=\"ul\">{`of one of the follow formats: JPEG, PNG, WebP, TIFF, GIF or SVG.`}</li>\n    </ul>\n    <pre><code parentName=\"pre\" {...{\n        \"className\": \"language-js\"\n      }}>{`plugins: [\n    {\n      resolve: 'gatsby-theme-carbon',\n      options: {\n        iconPath: './src/images/custom-icon-512.png'\n      },\n    },\n  ],\n`}</code></pre>\n    <h2 {...{\n      \"id\": \"additional-font-weights\"\n    }}>{`Additional font weights`}</h2>\n    <p>{`If needed, you can add support for additional Plex font weights. Don’t forget to specify italics for the additional weights if needed.`}</p>\n    <pre><code parentName=\"pre\" {...{\n        \"className\": \"language-js\"\n      }}>{`plugins: [\n    {\n      resolve: 'gatsby-theme-carbon',\n      options: {\n        // will get added to default [300, 400, 600]\n        additionalFontWeights: ['200', '200i]\n      },\n    },\n  ],\n`}</code></pre>\n    <h2 {...{\n      \"id\": \"image-compression\"\n    }}>{`Image Compression`}</h2>\n    <p>{`You can enable WebP by passing `}<inlineCode parentName=\"p\">{`withWebp: true`}</inlineCode>{` or providing your own optimization level. See the gatsby-remark-images `}<a parentName=\"p\" {...{\n        \"href\": \"https://www.gatsbyjs.org/packages/gatsby-remark-images/#options\"\n      }}>{`plugin options`}</a>{`.`}</p>\n    <pre><code parentName=\"pre\" {...{\n        \"className\": \"language-js\"\n      }}>{`module.exports = {\n  siteMetadata: {\n    title: 'Gatsby Theme Carbon',\n  },\n  plugins: [\n    {\n      resolve: 'gatsby-theme-carbon',\n      options: {\n        name: 'Gatsby Theme Carbon Starter',\n        shortName: 'Carbon Starter',\n        withWebp: true,\n      },\n    },\n  ],\n};\n`}</code></pre>\n    <h2 {...{\n      \"id\": \"global-search\"\n    }}>{`Global Search`}</h2>\n    <p>{`The GlobalSearch component is disabled by default. If you’d like to implement search functionality, you’ll need to follow these two steps:`}</p>\n    <ol>\n      <li parentName=\"ol\">{`set the isSearchEnabled theme option to true`}</li>\n    </ol>\n    <pre><code parentName=\"pre\" {...{\n        \"className\": \"language-js\"\n      }}>{`  plugins: [\n    {\n      resolve: 'gatsby-theme-carbon',\n      options: {\n        isSearchEnabled: true\n      },\n    },\n  ],\n`}</code></pre>\n    <ol {...{\n      \"start\": 2\n    }}>\n      <li parentName=\"ol\">{`Shadow the example search implementation at `}<inlineCode parentName=\"li\">{`/src/util/hooks/useSearch.js`}</inlineCode></li>\n    </ol>\n    <pre><code parentName=\"pre\" {...{\n        \"className\": \"language-jsx\"\n      }}>{`import { useEffect } from 'react';\nconst useAlgoliaSearch = () => {\n  // ...\n};\n\nexport default useAlgoliaSearch;\n`}</code></pre>\n    <p>{`The example `}<inlineCode parentName=\"p\">{`useSearch`}</inlineCode>{` hook demonstrates implementing search with `}<a parentName=\"p\" {...{\n        \"href\": \"https://www.algolia.com/\"\n      }}>{`Algolia`}</a>{`. Algolia is free for open source libraries. You can shadow this hook and replace it with your Algolia credentials or a library of your choosing.`}</p>\n    <h2 {...{\n      \"id\": \"edit-on-github-link\"\n    }}>{`Edit on GitHub link`}</h2>\n    <p>{`To add a link to the bottom of each page that points to the current page source in GitHub, provide an `}<inlineCode parentName=\"p\">{`repository`}</inlineCode>{` object to `}<inlineCode parentName=\"p\">{`siteMetadata`}</inlineCode>{` in your `}<inlineCode parentName=\"p\">{`gatsby-config.js`}</inlineCode>{` file. You can provide a `}<inlineCode parentName=\"p\">{`baseUrl`}</inlineCode>{`, and if needed, the `}<inlineCode parentName=\"p\">{`subDirectory`}</inlineCode>{` where your site source lives.`}</p>\n    <pre><code parentName=\"pre\" {...{\n        \"className\": \"language-js\"\n      }}>{`  plugins: [\n    {\n      resolve: 'gatsby-theme-carbon',\n      options: {\n        repository: {\n          baseUrl: 'https://github.com/carbon-design-system/gatsby-theme-carbon',\n          subDirectory: '/packages/example',\n        },\n      },\n    },\n  ],\n`}</code></pre>\n\n    </MDXLayout>;\n}\n\n;\nMDXContent.isMDXComponent = true;"}}